brel/__init__.py
brel/__main__.py
brel/brel_component.py
brel/brel_context.py
brel/brel_fact.py
brel/brel_filing.py
brel/cli.py
brel/qname.py
brel/characteristics/__init__.py
brel/characteristics/brel_aspect.py
brel/characteristics/concept_characteristic.py
brel/characteristics/entity_characteristic.py
brel/characteristics/explicit_dimension_characteristic.py
brel/characteristics/i_characteristic.py
brel/characteristics/period_characteristic.py
brel/characteristics/typed_dimension_characteristic.py
brel/characteristics/unit_characteristic.py
brel/config/__init__.py
brel/config/linkconfig.json
brel/config/nsconfig.json
brel/networks/__init__.py
brel/networks/calculation_network.py
brel/networks/calculation_network_node.py
brel/networks/definition_network.py
brel/networks/definition_network_node.py
brel/networks/footnote_network.py
brel/networks/footnote_network_node.py
brel/networks/i_network.py
brel/networks/i_network_node.py
brel/networks/label_network.py
brel/networks/label_network_node.py
brel/networks/presentation_network.py
brel/networks/presentation_network_node.py
brel/networks/reference_network.py
brel/networks/reference_network_node.py
brel/parsers/__init__.py
brel/parsers/i_filing_parser.py
brel/parsers/xml_filing_parser.py
brel/parsers/XML/__init__.py
brel/parsers/XML/xml_component_parser.py
brel/parsers/XML/xml_context_parser.py
brel/parsers/XML/xml_facts_parser.py
brel/parsers/XML/xml_namespace_normalizer.py
brel/parsers/XML/xml_report_element_factory.py
brel/parsers/XML/xml_report_element_parser.py
brel/parsers/XML/xml_sanity_checks.py
brel/parsers/XML/characteristics/__init__.py
brel/parsers/XML/characteristics/xml_parse_entity.py
brel/parsers/XML/characteristics/xml_parse_explicit_dimension.py
brel/parsers/XML/characteristics/xml_parse_period.py
brel/parsers/XML/characteristics/xml_parse_typed_dimension.py
brel/parsers/XML/characteristics/xml_parse_unit.py
brel/parsers/XML/networks/__init__.py
brel/parsers/XML/networks/i_xml_network_factory.py
xbrel-0.0.3.dist-info/METADATA
xbrel-0.0.3.dist-info/WHEEL
xbrel-0.0.3.dist-info/top_level.txt
xbrel-0.0.3.dist-info/RECORD
