Metadata-Version: 2.4
Name: xbrel
Version: 0.0.3
Summary: xbrl for SEC reader with code fixes
Author-email: Zappos <devzappos@gmail.com>
License: MIT
Project-URL: Homepage, https://github.com
Requires-Python: >=3.8
